setup.py
django_i18n_attrhelpers/__init__.py
django_i18n_attrhelpers/fields.py
django_i18n_attrhelpers/manager.py
django_i18n_attrhelpers/models.py
django_i18n_attrhelpers.egg-info/PKG-INFO
django_i18n_attrhelpers.egg-info/SOURCES.txt
django_i18n_attrhelpers.egg-info/dependency_links.txt
django_i18n_attrhelpers.egg-info/requires.txt
django_i18n_attrhelpers.egg-info/top_level.txt
django_i18n_attrhelpers/locale/de/LC_MESSAGES/django.mo
django_i18n_attrhelpers/locale/de/LC_MESSAGES/django.po