Metadata-Version: 1.1
Name: django-i18n-attrhelpers
Version: 0.1.1-2
Summary: Helpers for accessing ..._$LANG-fields
Home-page: https://github.com/ddanier/django_i18n_attrhelpers
Author: David Danier
Author-email: david.danier@team23.de
License: UNKNOWN
Platform: UNKNOWN
Classifier: Development Status :: 4 - Beta
Classifier: Environment :: Web Environment
Classifier: Framework :: Django
Classifier: Intended Audience :: Developers
Classifier: License :: OSI Approved :: BSD License
Classifier: Operating System :: OS Independent
Classifier: Programming Language :: Python
Classifier: Topic :: Utilities
